hamel_deck_of_cards/__init__.py
hamel_deck_of_cards/_modidx.py
hamel_deck_of_cards/card.py
hamel_deck_of_cards/deck.py
hamel_deck_of_cards-0.0.1.dist-info/LICENSE
hamel_deck_of_cards-0.0.1.dist-info/METADATA
hamel_deck_of_cards-0.0.1.dist-info/WHEEL
hamel_deck_of_cards-0.0.1.dist-info/entry_points.txt
hamel_deck_of_cards-0.0.1.dist-info/top_level.txt
hamel_deck_of_cards-0.0.1.dist-info/RECORD
