Metadata-Version: 2.1
Name: hamel-deck-of-cards
Version: 0.0.1
Summary: An example repository for nbdev
Home-page: https://github.com/fastai/hamel_deck_of_cards/tree/main/
Author: Isaac Flath
Author-email: dev@fast.ai
License: Apache Software License 2.0
Keywords: nbdev
Platform: UNKNOWN
Classifier: Development Status :: 3 - Alpha
Classifier: Intended Audience :: Developers
Classifier: Natural Language :: English
Classifier: Programming Language :: Python :: 3.7
Classifier: Programming Language :: Python :: 3.8
Classifier: License :: OSI Approved :: Apache Software License
Requires-Python: >=3.7
License-File: LICENSE
Requires-Dist: fastcore
Provides-Extra: dev
Requires-Dist: plotly (==5.5.0) ; extra == 'dev'
Requires-Dist: pandas (==1.4.3) ; extra == 'dev'
Requires-Dist: nbformat (>=4.2.0) ; extra == 'dev'
